sp_post.cpython-38-x86_64-linux-gnu.so
sp_post-0.0.3.dist-info/METADATA
sp_post-0.0.3.dist-info/WHEEL
sp_post-0.0.3.dist-info/top_level.txt
sp_post-0.0.3.dist-info/RECORD
