Metadata-Version: 2.1
Name: sp-post
Version: 0.0.3
Summary: sp_post process
Home-page: UNKNOWN
Author: xinli
Author-email: lisin97@pku.edu.cn
License: UNKNOWN
Platform: UNKNOWN
